erosolar_browser/__init__.py
erosolar_browser-1.0.2.dist-info/METADATA
erosolar_browser-1.0.2.dist-info/WHEEL
erosolar_browser-1.0.2.dist-info/top_level.txt
erosolar_browser-1.0.2.dist-info/RECORD
