Metadata-Version: 2.4
Name: erosolar-browser
Version: 1.0.2
Summary: Python SDK to automate the EroSolar AI Browser - control a visible browser with AI
Author-email: Bo Shang <bo@shang.software>
License: MIT
Project-URL: Homepage, https://americaisfinallyback.com
Project-URL: Repository, https://github.com/AmerisFinally/erosolar-browser
Project-URL: Documentation, https://americaisfinallyback.com/downloads
Keywords: browser,automation,ai,gpt,selenium,playwright
Classifier: Development Status :: 4 - Beta
Classifier: Intended Audience :: Developers
Classifier: License :: OSI Approved :: MIT License
Classifier: Programming Language :: Python :: 3
Classifier: Programming Language :: Python :: 3.8
Classifier: Programming Language :: Python :: 3.9
Classifier: Programming Language :: Python :: 3.10
Classifier: Programming Language :: Python :: 3.11
Classifier: Programming Language :: Python :: 3.12
Classifier: Topic :: Internet :: WWW/HTTP :: Browsers
Classifier: Topic :: Software Development :: Testing
Requires-Python: >=3.8
Requires-Dist: requests>=2.25.0
Provides-Extra: dev
Requires-Dist: pytest; extra == "dev"
Requires-Dist: black; extra == "dev"
Requires-Dist: twine; extra == "dev"
Requires-Dist: build; extra == "dev"
